setmail/__init__.py
SetMail-0.1.dist-info/METADATA
SetMail-0.1.dist-info/WHEEL
SetMail-0.1.dist-info/top_level.txt
SetMail-0.1.dist-info/RECORD
