Metadata-Version: 2.1
Name: SetMail
Version: 0.1
Summary: Minimalist email sending for Python — just import and send
Home-page: https://pypi.org/project/SetMail/
Author: Your Name
Author-email: your@email.com
License: UNKNOWN
Platform: UNKNOWN
Classifier: Programming Language :: Python :: 3
Classifier: License :: OSI Approved :: MIT License
Requires-Python: >=3.7
